scr/spinfinder/__init__.py
scr/spinfinder/spinfinder.py
scr/spinfinder/.ipynb_checkpoints/Untitled-checkpoint.ipynb
scr/spinfinder/.ipynb_checkpoints/Untitled1-checkpoint.ipynb
scr/spinfinder/.ipynb_checkpoints/gen_str-checkpoint.py
spinfinder-0.0.3.dist-info/METADATA
spinfinder-0.0.3.dist-info/WHEEL
spinfinder-0.0.3.dist-info/licenses/LICENSE
spinfinder-0.0.3.dist-info/RECORD
