Metadata-Version: 2.1
Name: spinfinder
Version: 0.0.3
Summary: Calculate the spin multiplicity of your PAH fast using Ovchinnikov's rule.
Author-email: Stiv Llenga <stiv.llenga@h-its.org>
License-File: LICENSE
Classifier: License :: OSI Approved :: MIT License
Classifier: Operating System :: OS Independent
Classifier: Programming Language :: Python :: 3
Requires-Python: >=3.7
